snmpsim/__init__.py
snmpsim/confdir.py
snmpsim/controller.py
snmpsim/daemon.py
snmpsim/datafile.py
snmpsim/endpoints.py
snmpsim/error.py
snmpsim/log.py
snmpsim/utils.py
snmpsim/variation.py
snmpsim/commands/__init__.py
snmpsim/commands/cmd2rec.py
snmpsim/commands/mib2rec.py
snmpsim/commands/pcap2rec.py
snmpsim/commands/rec2rec.py
snmpsim/commands/responder.py
snmpsim/commands/responder_lite.py
snmpsim/grammar/__init__.py
snmpsim/grammar/abstract.py
snmpsim/grammar/dump.py
snmpsim/grammar/mvc.py
snmpsim/grammar/sap.py
snmpsim/grammar/snmprec.py
snmpsim/grammar/walk.py
snmpsim/record/__init__.py
snmpsim/record/abstract.py
snmpsim/record/dump.py
snmpsim/record/mvc.py
snmpsim/record/sap.py
snmpsim/record/snmprec.py
snmpsim/record/walk.py
snmpsim/record/search/__init__.py
snmpsim/record/search/database.py
snmpsim/record/search/file.py
snmpsim/reporting/__init__.py
snmpsim/reporting/manager.py
snmpsim/reporting/formats/__init__.py
snmpsim/reporting/formats/alljson.py
snmpsim/reporting/formats/base.py
snmpsim/reporting/formats/null.py
thola_snmpsim-1.0.0.data/data/snmpsim/data/public.snmprec
thola_snmpsim-1.0.0.data/data/snmpsim/data/1.3.6.1.6.1.1.0/127.0.0.1.snmprec
thola_snmpsim-1.0.0.data/data/snmpsim/data/foreignformats/linux.snmpwalk
thola_snmpsim-1.0.0.data/data/snmpsim/data/foreignformats/winxp1.snmpwalk
thola_snmpsim-1.0.0.data/data/snmpsim/data/foreignformats/winxp2.sapwalk
thola_snmpsim-1.0.0.data/data/snmpsim/data/mib2dev/host-resources-mib.snmprec
thola_snmpsim-1.0.0.data/data/snmpsim/data/mib2dev/ip-mib.snmprec
thola_snmpsim-1.0.0.data/data/snmpsim/data/mib2dev/tcp-mib.snmprec
thola_snmpsim-1.0.0.data/data/snmpsim/data/mib2dev/udp-mib.snmprec
thola_snmpsim-1.0.0.data/data/snmpsim/data/public/1.3.6.1.2.1.100.1.13.0.snmprec
thola_snmpsim-1.0.0.data/data/snmpsim/data/public/1.3.6.1.2.1.100.1.2.0/__1.snmprec
thola_snmpsim-1.0.0.data/data/snmpsim/data/public/1.3.6.1.6.1.1.0/127.0.0.1.snmprec
thola_snmpsim-1.0.0.data/data/snmpsim/data/recorded/apc-ap7902b.snmprec
thola_snmpsim-1.0.0.dist-info/LICENSE.txt
thola_snmpsim-1.0.0.dist-info/METADATA
thola_snmpsim-1.0.0.dist-info/WHEEL
thola_snmpsim-1.0.0.dist-info/entry_points.txt
thola_snmpsim-1.0.0.dist-info/top_level.txt
thola_snmpsim-1.0.0.dist-info/RECORD
